droptopus/__init__.py
droptopus/__main__.py
droptopus/__version__.py
droptopus/app.py
droptopus/args.py
droptopus/config.py
droptopus/forms.py
droptopus/settings.py
droptopus/utils.py
droptopus/widgets.py
droptopus/window.py
droptopus/assets/7zip.png
droptopus/assets/accept_database.png
droptopus/assets/add_database.png
droptopus/assets/add_file.png
droptopus/assets/add_folder.png
droptopus/assets/add_to_favorites.png
droptopus/assets/address_book.png
droptopus/assets/app.css
droptopus/assets/apple.png
droptopus/assets/apple_2.png
droptopus/assets/archive.png
droptopus/assets/binders.png
droptopus/assets/block.png
droptopus/assets/briefcase.png
droptopus/assets/bug.png
droptopus/assets/burn.png
droptopus/assets/burn_cd.png
droptopus/assets/calendar.png
droptopus/assets/cards.png
droptopus/assets/cd.png
droptopus/assets/cherry.png
droptopus/assets/chrome.png
droptopus/assets/circled_play.png
droptopus/assets/clock-in.png
droptopus/assets/clock-out.png
droptopus/assets/close_window.png
droptopus/assets/close_window_white.png
droptopus/assets/cloud.png
droptopus/assets/cloud_storage.png
droptopus/assets/clubs_filled.png
droptopus/assets/command_line.png
droptopus/assets/console.png
droptopus/assets/create_archive.png
droptopus/assets/day_of_the_tentacle.png
droptopus/assets/desktop.png
droptopus/assets/deviantart.png
droptopus/assets/diamonds.png
droptopus/assets/dice.png
droptopus/assets/documents.png
droptopus/assets/dossier.png
droptopus/assets/downloads.png
droptopus/assets/dribbble.png
droptopus/assets/dropbox.png
droptopus/assets/droptopus.png
droptopus/assets/export.png
droptopus/assets/extensions.png
droptopus/assets/facebook.png
droptopus/assets/favorite.png
droptopus/assets/favorite_file.png
droptopus/assets/feedly.png
droptopus/assets/filing_cabinet.png
droptopus/assets/fingerprint.png
droptopus/assets/firefox.png
droptopus/assets/firewall.png
droptopus/assets/forrst.png
droptopus/assets/google_drive.png
droptopus/assets/google_photos.png
droptopus-0.2.65.dist-info/LICENSE.md
droptopus-0.2.65.dist-info/METADATA
droptopus-0.2.65.dist-info/WHEEL
droptopus-0.2.65.dist-info/entry_points.txt
droptopus-0.2.65.dist-info/top_level.txt
droptopus-0.2.65.dist-info/RECORD
