Metadata-Version: 2.1
Name: droptopus
Version: 0.2.65
Summary: Droptopus is a drag'n'drop router, which routes dropped objects to the designated actions
Home-page: https://github.com/ArtBIT/Droptopus
Author: Djordje Ungar
Author-email: mail@djordjeungar.com
License: MIT
Project-URL: Bug Reports, https://github.com/ArtBIT/Droptopus/issues
Project-URL: Say Thanks!, http://saythanks.io/to/ArtBIT
Project-URL: Source, https://github.com/ArtBIT/Droptopus/
Keywords: sample setuptools development
Classifier: Development Status :: 4 - Beta
Classifier: License :: OSI Approved :: MIT License
Classifier: Programming Language :: Python :: 3.5
Classifier: Programming Language :: Python :: 3.6
Classifier: Programming Language :: Python :: 3.7
License-File: LICENSE.md
Requires-Dist: PyQt5
Requires-Dist: python-magic
Requires-Dist: requests >=2.21.0
Requires-Dist: urllib3 ==1.26.5
